valohai_yaml/__init__.py
valohai_yaml/__main__.py
valohai_yaml/commands.py
valohai_yaml/excs.py
valohai_yaml/lint.py
valohai_yaml/parsing.py
valohai_yaml/py.typed
valohai_yaml/schema_data.py
valohai_yaml/types.py
valohai_yaml/validation.py
valohai_yaml/objs/__init__.py
valohai_yaml/objs/base.py
valohai_yaml/objs/config.py
valohai_yaml/objs/deployment.py
valohai_yaml/objs/endpoint.py
valohai_yaml/objs/environment_variable.py
valohai_yaml/objs/file.py
valohai_yaml/objs/input.py
valohai_yaml/objs/mount.py
valohai_yaml/objs/parameter.py
valohai_yaml/objs/parameter_map.py
valohai_yaml/objs/parameter_widget.py
valohai_yaml/objs/step.py
valohai_yaml/objs/task.py
valohai_yaml/objs/utils.py
valohai_yaml/objs/variant_parameter.py
valohai_yaml/objs/workload_resources.py
valohai_yaml/objs/pipelines/__init__.py
valohai_yaml/objs/pipelines/deployment_node.py
valohai_yaml/objs/pipelines/edge.py
valohai_yaml/objs/pipelines/edge_merge_mode.py
valohai_yaml/objs/pipelines/execution_node.py
valohai_yaml/objs/pipelines/node.py
valohai_yaml/objs/pipelines/node_action.py
valohai_yaml/objs/pipelines/override.py
valohai_yaml/objs/pipelines/pipeline.py
valohai_yaml/objs/pipelines/pipeline_parameter.py
valohai_yaml/objs/pipelines/task_node.py
valohai_yaml/objs/pipelines/types.py
valohai_yaml/objs/pipelines/validation.py
valohai_yaml/pipelines/__init__.py
valohai_yaml/pipelines/conversion.py
valohai_yaml/utils/__init__.py
valohai_yaml/utils/duration.py
valohai_yaml/utils/lint.py
valohai_yaml/utils/merge.py
valohai_yaml/utils/node_socket_utils.py
valohai_yaml/utils/terminal.py
valohai_yaml/utils/markdown_doc/__init__.py
valohai_yaml/utils/markdown_doc/doc_generator.py
valohai_yaml/utils/markdown_doc/formatters.py
valohai_yaml/utils/markdown_doc/parsers.py
valohai_yaml/utils/markdown_doc/types.py
valohai_yaml-0.53.0.dist-info/METADATA
valohai_yaml-0.53.0.dist-info/WHEEL
valohai_yaml-0.53.0.dist-info/entry_points.txt
valohai_yaml-0.53.0.dist-info/licenses/LICENSE
valohai_yaml-0.53.0.dist-info/RECORD
