Metadata-Version: 2.4
Name: valohai-yaml
Version: 0.53.0
Summary: Valohai.yaml validation and parsing
Project-URL: Homepage, https://github.com/valohai/valohai-yaml
Author-email: Valohai <info@valohai.com>
License-Expression: MIT
License-File: LICENSE
Keywords: strings,utility
Classifier: Development Status :: 5 - Production/Stable
Classifier: License :: OSI Approved :: MIT License
Classifier: Natural Language :: English
Classifier: Programming Language :: Python :: 3.9
Classifier: Programming Language :: Python :: 3.10
Classifier: Programming Language :: Python :: 3.11
Classifier: Programming Language :: Python :: 3.12
Classifier: Programming Language :: Python :: 3.13
Classifier: Topic :: Software Development :: Libraries
Requires-Python: >=3.9
Requires-Dist: jsonschema>=4.0
Requires-Dist: leval>=1.1.1
Requires-Dist: pyyaml
